Metadata-Version: 2.1
Name: lexicographic-encoding
Version: 0.1.1
Summary: Encode tuples of primitive types into bytestrings preserving the lexicographic order
Home-page: https://gitlab.com/dlnet/lexicographic-encoding.git
Author: Dario Balboni
Author-email: dario.balboni.96+lexenc@gmail.com
License: GPL-3.0
Platform: UNKNOWN
Classifier: Programming Language :: Python :: 3
Classifier: License :: OSI Approved :: GNU General Public License v3 (GPLv3)
Classifier: Operating System :: OS Independent
Classifier: Development Status :: 4 - Beta
Classifier: Intended Audience :: Developers
Classifier: Topic :: Utilities
Requires-Python: >=3.6
License-File: LICENSE
